pytest_html/__init__.py
pytest_html/__version.py
pytest_html/basereport.py
pytest_html/extras.py
pytest_html/fixtures.py
pytest_html/hooks.py
pytest_html/plugin.py
pytest_html/report.py
pytest_html/report_data.py
pytest_html/selfcontained_report.py
pytest_html/util.py
pytest_html/resources/app.js
pytest_html/resources/index.jinja2
pytest_html/resources/style.css
pytest_html-4.0.1.dist-info/METADATA
pytest_html-4.0.1.dist-info/WHEEL
pytest_html-4.0.1.dist-info/entry_points.txt
pytest_html-4.0.1.dist-info/licenses/LICENSE
pytest_html-4.0.1.dist-info/RECORD
